Workbook

Sheet Calendar
A1: META Events & Conferences Calendar
A2: Lenovo RHQ Riyadh - Market Intelligence | Last updated: 2026-10-27 | Status colours and summary: see the Overview sheet
A3: Risk note: Riyadh event attrition continues: GAIN Summit (to Sep 2027), Cityscape Global (to 1-4 Feb 2027), FII10, UN World Data Forum, Intersec Saudi, Saudi Retail Forum and Security Middle East Conference are all moved; non-tech Riyadh and Qiddiya events (Asian Indoor Games, Extreme H) followed on 26-27 Oct. Houthi attacks near Ras Tanura and on Aramco offices (27 Oct), the US ordered-departure notice and RUH operations shifted to Al Qassim until about 7 Nov remain the backdrop. Counter-signal: MOI/Tahaluf continue with GSTS (1 Nov-20 Dec) and SAIF (24-26 Nov). Black Hat MEA (1-3 Dec) shows no notice but shares organiser and venue with Cityscape. Biban 2026 has no 2026 coverage. Dubai is becoming the main regional stage: GITEX Global (7-11 Dec) lists Huawei and Supermicro but not Lenovo. Live venues outside KSA: Cityscape Qatar (to 29 Oct), ADIPEC (2-5 Nov), Cairo ICT (7-10 Nov), MWC26 Doha (8-10 Nov), World Police Summit and the Abu Dhabi DC events (16-19 Nov).
A5: Event | B5: Start date | C5: End date | D5: Days to start | E5: Dates (as reported) | F5: Status | G5: Region | H5: Country | I5: City / venue | J5: Lenovo BU relevance | K5: Key accounts / competitors | L5: Action | M5: Source + verified on
A6: Cityscape Qatar 2026 | B6: 46322 | C6: 46324 | D6: =IF(B6="","",B6-TODAY()) -> 0 | E6: 27-29 Oct 2026 | F6: Upcoming - live 27-29 Oct | G6: GCC | H6: Qatar | I6: Doha, DECC | J6: SSG (smart buildings), minor | K6: Qatar developers; Ooredoo (sponsor); 400+ projects showcased | L6: Note only | M6: Xinhua 27 Oct 16:14 KSA; Gulf Times 27 Oct; cityscape-events.com/qatar checked 21 Oct
A7: Apple 'Pro and tell' event | B7: 46323 | C7: 46323 | D7: =IF(B7="","",B7-TODAY()) -> 1 | E7: 46323 | F7: Upcoming | G7: Global | H7: USA | I7: Los Angeles (venue not specified) | J7: IDG (premium notebooks) | K7: Apple | L7: Prepare ThinkPad X1 / Yoga counter-message for a rumoured OLED touchscreen MacBook Pro | M7: Reuters via The Daily Guardian 19 Oct; multiple outlets 21-22 Oct 2026; confirmed, multiple outlets 23-24 Oct 2026
A8: Microsoft FY27 Q1 earnings | B8: 46323 | C8: 46323 | D8: =IF(B8="","",B8-TODAY()) -> 1 | E8: 28 Oct 2026 after US close; webcast 29 Oct 00:30 KSA | F8: Upcoming | G8: Global | H8: USA | I8: Redmond (webcast) | J8: ISG/SSG (Azure Local; Azure KSA region) | K8: Microsoft | L8: Watch Azure capex and KSA region commentary | M8: Microsoft IR release 7 Oct 2026
A9: SK hynix Q3 2026 earnings call | B9: 46323 | C9: 46323 | D9: =IF(B9="","",B9-TODAY()) -> 1 | E9: 28 Oct 2026, 09:00 KST (03:00 KSA) | F9: Upcoming | G9: Global | H9: South Korea | I9: Seoul (call) | J9: ISG/IDG (memory cost, HBM supply) | K9: SK hynix | L9: Capture DRAM/HBM pricing and LTA commentary for META pricing guidance | M9: SK hynix invitation; Chosun 25 Oct 2026
A10: Samsung Electronics Q3 2026 earnings call | B10: 46324 | C10: 46324 | D10: =IF(B10="","",B10-TODAY()) -> 2 | E10: 29 Oct 2026, 10:00 KST (04:00 KSA) | F10: Upcoming - watch (date conflict: 29 Oct per Samsung IR vs 30 Oct per aggregator) | G10: Global | H10: South Korea | I10: Seoul (webcast) | J10: ISG/IDG (memory) | K10: Samsung | L10: Capture LTA share, HBM4 and DRAM pricing commentary; preliminary Q3 OP ~KRW 107.4tn | M10: samsung.com/global/ir events page, read 26 Oct 2026
A11: GSTS Month (Global Security & Technology Summit programme) | B11: 46327 | C11: 46356 | D11: =IF(B11="","",B11-TODAY()) -> 5 | E11: 1-30 Nov 2026, 13 administrative regions | F11: Upcoming - watch | G11: KSA | H11: Saudi Arabia | I11: KSA-wide | J11: SSG (public safety); IDG (education) | K11: MOI, Tuwaiq Academy, MOE, Elm, Tahakom; producer Tahaluf | L11: Approach Elm/Tahakom for partner slots (OPP-116) | M11: SPA N2709441, 25 Oct 2026 01:13 KSA
A12: ADIPEC 2026 | B12: 46328 | C12: 46331 | D12: =IF(B12="","",B12-TODAY()) -> 6 | E12: 2-5 Nov 2026 | F12: Upcoming | G12: GCC | H12: UAE | I12: Abu Dhabi, ADNEC | J12: ISG/SSG (energy digital, edge, HPC) | K12: ADNOC, Aramco delegations | L12: Energy-AI outreach; use ADIPEC Global Energy Report (81% expect AI power demand to beat forecasts) in Neptune/efficiency messaging | M12: adipec.com 20 Oct; The National 22 Oct 2026 10:15 KSA
A13: Biban 2026 | B13: 46331 | C13: 46334 | D13: =IF(B13="","",B13-TODAY()) -> 9 | E13: 5-8 Nov 2026 (calendar listing only) | F13: Dates unconfirmed - at risk, watch | G13: KSA | H13: Saudi Arabia | I13: Riyadh (venue conflict: Riyadh Front vs Malham) | J13: IDG (SME) | K13: Monsha'at, SMEs | L13: Verify on the Monsha'at site; the 5-8 Nov listing is likely carried over from Biban 2025 (closed about 8-9 Nov 2025) | M13: Google News AR/EN: no 2026 coverage, latest items are Biban 2025 (SPA 8 Nov 2025); checked 27 Oct 2026
A14: Cairo ICT 2026 (30th) | B14: 46333 | C14: 46336 | D14: =IF(B14="","",B14-TODAY()) -> 11 | E14: 7-10 Nov 2026 (corrected from 8-11 Nov; official site) | F14: Upcoming | G14: MEA | H14: Egypt | I14: New Cairo, Egypt International Exhibition Center | J14: IDG/ISG (Egypt public sector, telcos) | K14: MCIT Egypt, Telecom Egypt, Vodafone/Orange Egypt; Dell (Title), Huawei (Technology), e-finance (Strategic), MIDAR (Master), Fortinet (Security), CIB and Egypt Trust (Platinum), Noventiq, ICT Misr/IoT Misr, Canon; Cisco exhibiting with CONNECT-PS; no Lenovo | L14: Counter Dell's title sponsorship: decide this week on a partner/side-event slot or off-site Egypt executive meetings | M14: cairoict.com read 25 Oct 2026; FinTech Gate 25 Oct 10:00 KSA
A15: MWC26 Doha | B15: 46334 | C15: 46336 | D15: =IF(B15="","",B15-TODAY()) -> 12 | E15: 8-10 Nov 2026 (showfloor sold out) | F15: Upcoming | G15: GCC | H15: Qatar | I15: Doha, DECC | J15: SSG/ISG (telco, 5G/edge); IDG | K15: MCIT Qatar, Ooredoo, Vodafone Qatar, GSMA; Huawei (promoted exhibitor), Nokia, Ericsson; Oliver Wyman (Agentic AI Summit); co-located with ITU PP-26 | L15: Telco and edge meetings; book Mannai (Cisco sovereign AI partner) and Meeza; note Qatar MotoGP 6-8 Nov overlap and reported rider safety dispute | M15: mwcdoha.com read 26 Oct 2026 (structured-data end date 11 Nov still conflicts)
A16: ITU Plenipotentiary Conference (PP-26) | B16: 46335 | C16: 46353 | D16: =IF(B16="","",B16-TODAY()) -> 13 | E16: 9-27 Nov 2026 | F16: Upcoming - watch | G16: GCC | H16: Qatar | I16: Doha, DECC | J16: Policy context (telecom ministers) | K16: CRA Qatar, regional ICT ministers incl. MCIT KSA | L16: Watch for ministerial announcements and MoUs on the sidelines | M16: QNA 31 Aug 2026
A17: Web Summit 2026 (Lisbon) | B17: 46335 | C17: 46338 | D17: =IF(B17="","",B17-TODAY()) -> 13 | E17: 9-12 Nov 2026 | F17: Upcoming - watch | G17: Global | H17: Portugal | I17: Lisbon (venue not stated on page) | J17: SSG/IDG (startups, investors) | K17: Web Summit Qatar organiser; Gulf SWFs and VCs | L17: Watch for Gulf investor and Web Summit Qatar 2027 announcements | M17: websummit.com read 27 Oct 2026
A18: SC26 (Supercomputing) | B18: 46341 | C18: 46346 | D18: =IF(B18="","",B18-TODAY()) -> 19 | E18: 15-20 Nov 2026 (exhibits 17-19 Nov) | F18: Upcoming | G18: Global | H18: USA | I18: Chicago, McCormick Place | J18: ISG (HPC, Neptune, TOP500) | K18: Dell, HPE, Supermicro, NVIDIA; KAUST and Aramco HPC teams | L18: Prepare TOP500/HPC counter-messaging for KSA HPC accounts | M18: sc26.supercomputing.org, 19 Oct 2026 (venue corrected 22 Oct)
A19: World Police Summit 2026 | B19: 46342 | C19: 46344 | D19: =IF(B19="","",B19-TODAY()) -> 20 | E19: 16-18 Nov 2026 | F19: Upcoming | G19: GCC | H19: UAE | I19: Dubai World Trade Centre | J19: SSG (safe city, public safety); IDG rugged | K19: Dubai Police, UAE MOI, GCC police forces; Samsung (Headline), Presight/G42 (Intelligence Partner), airobotics, Dahua, Axon, Convergint, ENBD | L19: Counter Samsung headline position; book Dubai Police / MOI meetings (OPP-112) | M19: worldpolicesummit.com read 25 Oct 2026 (Arabic header shows 23-25 Jun 2026, conflicts with English FAQ)
... A38: Cityscape Global 2026 | B38: 46419 | C38: 46422 | D38: =IF(B38="","",B38-TODAY()) -> 97 | E38: 1-4 Feb 2027 (moved from 16-19 Nov 2026; 2027 edition unchanged 15-18 Nov 2027) | F38: Postponed - moved to Feb 2027 | G38: KSA | H38: Saudi Arabia | I38: Riyadh, RECC Malham | J38: IDG/SSG (smart buildings, giga-projects) | K38: ROSHN, NHC, giga-project developers; speakers: Ministers Al-Hogail and Al-Saif, NHC CEO, Diriyah, New Murabba, PIF real estate, Aramco Digital board member | L38: Convert mid-Nov giga-project meetings (ROSHN, NHC, Diriyah) into direct account visits; re-plan for Feb 2027; leading indicator for Black Hat MEA (same organiser and venue) | M38: Sabq 26 Oct 2026 19:15 KSA (https://sabq.org/article/dli2joy); cityscapeglobal.com notice (undated) read 26 Oct 2026
A39: 6th Asian Indoor & Martial Arts Games (non-tech) | B39: 46474 | D39: =IF(B39="","",B39-TODAY()) -> 152 | E39: Was Nov 2026; rescheduled to start 28 Mar 2027 (end date not verified) | F39: Postponed | G39: KSA | H39: Saudi Arabia | I39: Riyadh | J39: None (Riyadh event-risk signal) | K39: - | L39: Context only | M39: Arab News 26 Oct 17:14 KSA; SPA 27 Oct 04:56 KSA
A40: LEAP 2027 | B40: 46489 | C40: 46492 | D40: =IF(B40="","",B40-TODAY()) -> 167 | E40: 12-15 Apr 2027 (with DeepFest) | F40: Upcoming - watch | G40: KSA | H40: Saudi Arabia | I40: Riyadh, RECC Malham | J40: IDG/ISG/SSG | K40: Tahaluf, MCIT, HUMAIN, hyperscalers | L40: Plan booth; watch Riyadh security | M40: onegiantleap.com read 22 Oct 2026 (Browser)
A41: Global Health Exhibition | B41: 46685 | C41: 46688 | D41: =IF(B41="","",B41-TODAY()) -> 363 | E41: Was 26-29 Oct 2026; now 25-28 Oct 2027 (2026 Digital Forum online, dates TBA) | F41: Postponed | G41: KSA | H41: Saudi Arabia | I41: Riyadh (venue not stated on new page) | J41: IDG/SSG (healthcare devices, hybrid cloud) | K41: MOH, health clusters | L41: Re-plan health-vertical outreach without the show; confirm via MOH/SPA | M41: globalhealthsaudi.com, verified 19 Oct 2026 (notice undated)
A42: Saudi Build 2026 + Saudi Elenex 2026 | B42: 46692 | C42: 46695 | D42: =IF(B42="","",B42-TODAY()) -> 370 | E42: Was 2-5 Nov 2026, now 1-4 Nov 2027 (19 Oct cached page says only 'next year') | F42: Postponed | G42: KSA | H42: Saudi Arabia | I42: Riyadh (Riyadh Exhibitions Co.) | J42: SSG (smart buildings), minor | K42: Construction and energy contractors | L42: Note only; leading indicator for other Riyadh trade shows | M42: TradeArabia 18 Oct 2026; IndexBox 18 Oct; checked 19 Oct 2026
A43: 2nd EU-GCC Summit | D43: =IF(B43="","",B43-TODAY()) | E43: Was 24 Oct 2026, now TBD | F43: Postponed | G43: KSA | H43: Saudi Arabia | I43: Riyadh | J43: Policy context | K43: GCC, EU | L43: Context | M43: The National / Saudi Gazette / Reuters, 15 Oct 2026; checked 18 Oct 2026
A44: 6th UN World Data Forum + 2nd Saudi Statistics Forum | D44: =IF(B44="","",B44-TODAY()) | E44: Was Nov 2026 (one listing: 9-12 Nov); postponed to 2027, dates TBA | F44: Postponed | G44: KSA | H44: Saudi Arabia | I44: Riyadh | J44: ISG/SSG (public-sector data, AI) | K44: GASTAT, SDAIA, UN Statistics Division | L44: Engage GASTAT/SDAIA one-to-one instead | M44: RFE/RL 23 Oct 07:17 KSA; Reuters 23 Oct; Arab News 23 Oct 11:19 KSA
A45: FIA Extreme H World Cup (non-tech) | D45: =IF(B45="","",B45-TODAY()) | E45: Was late Oct/Nov 2026; postponed to 2027, dates TBA | F45: Postponed | G45: KSA | H45: Saudi Arabia | I45: Qiddiya City | J45: None (event-risk signal) | K45: - | L45: Context only | M45: FIA 26 Oct 23:49 KSA; What's On Saudi Arabia 27 Oct
A46: FII10 - Future Investment Initiative | D46: =IF(B46="","",B46-TODAY()) | E46: Was 26-29 Oct 2026; postponed to 2027, dates TBA | F46: Postponed | G46: KSA | H46: Saudi Arabia | I46: Riyadh, King Abdulaziz International Conference Center (KAICC) | J46: ISG/SSG (sovereign AI, AI infrastructure); IDG | K46: PIF (Founding Partner), Aramco, HUMAIN, stc Group, NEOM, SoftBank Vision Fund, Brookfield; no hardware OEM listed | L46: Cancel or convert FII side meetings; re-engage PIF, HUMAIN, stc and Aramco one-to-one in Riyadh or at DCD>Connect MENA / GITEX Global | M46: fii-institute.org read 24 Oct 2026 (moving to 2027, no dates); Bloomberg 24 Oct confirms postponement
A47: GAIN Summit (4th Global AI Summit) | D47: =IF(B47="","",B47-TODAY()) | E47: Was 15-17 Sep 2026; rescheduled to Sep 2027 (days TBA) | F47: Postponed | G47: KSA | H47: Saudi Arabia | I47: Riyadh, KAICC | J47: ISG/SSG (sovereign AI) | K47: SDAIA, HUMAIN | L47: Engage SDAIA one-to-one; verify 2027 dates | M47: Arab News 1 Sep 2026 ('SDAIA reschedules fourth Global AI Summit to September 2027'); checked 27 Oct 2026
A48: IDEAS 2026 (defence exhibition) | D48: =IF(B48="","",B48-TODAY()) | E48: Was 24-27 Nov 2026; cancelled for 2026, next edition 2028 | F48: Postponed (cancelled for 2026) | G48: MEA | H48: Pakistan | I48: Karachi Expo Centre | J48: SSG (defence-tech), minor | K48: DEPO, MoD Production Pakistan | L48: Note only; regional event-risk signal | M48: ideaspakistan.gov.pk read 24 Oct 2026 (notice undated)
A49: Intersec Saudi Arabia 2026 | D49: =IF(B49="","",B49-TODAY()) | E49: Was 16-18 Nov 2026; now Oct 2027 (day TBA) | F49: Postponed | G49: KSA | H49: Saudi Arabia | I49: Riyadh | J49: SSG (safe city, public safety) | K49: Messe Frankfurt Saudi Arabia; MOI, civil defence | L49: Re-route safe-city pipeline to Milipol Qatar and Black Hat MEA | M49: Zawya (Messe Frankfurt release) 19 Oct 2026 15:20 KSA; The National 19 Oct
A50: Misk Global Forum 2026 | D50: =IF(B50="","",B50-TODAY()) | E50: Was 11-12 Nov 2026; cancelled for 2026 | F50: Postponed (cancelled for 2026) | G50: KSA | H50: Saudi Arabia | I50: Riyadh | J50: None (risk signal) | K50: - | L50: Context | M50: Arab News PK; Roya News, about 11-13 Oct 2026
A51: Saudi Retail Forum 2026 | D51: =IF(B51="","",B51-TODAY()) | E51: Was 19 Nov 2026; now Mar 2027 | F51: Postponed | G51: KSA | H51: Saudi Arabia | I51: Riyadh | J51: IDG/SSG (retail edge), minor | K51: KSA retailers | L51: Note only | M51: The National 19 Oct 2026 19:41 KSA
A52: Security Middle East Conference 2026 | D52: =IF(B52="","",B52-TODAY()) | E52: Was 28 Apr, then 29 Nov 2026; now 31 May 2027 (single source) | F52: Postponed | G52: KSA | H52: Saudi Arabia | I52: Riyadh, voco Riyadh | J52: SSG (security), minor | K52: Security professionals | L52: Note only; Riyadh risk signal | M52: Northstar Meetings Group (organiser statement); publish date unverified

Sheet Overview
A1: Overview
A3: Summary | B3: Count
A4: Events tracked | B4: =COUNTA(Calendar!$A$6:$A$52) -> 47
A5: Starting in the next 7 days | B5: =COUNTIFS(Calendar!$D$6:$D$52,">=0",Calendar!$D$6:$D$52,"<=7") -> 7
A6: Starting in the next 30 days | B6: =COUNTIFS(Calendar!$D$6:$D$52,">=0",Calendar!$D$6:$D$52,"<=30") -> 20
A7: At risk or on watch | B7: =COUNTIF(Calendar!$F$6:$F$52,"*risk*")+COUNTIF(Calendar!$F$6:$F$52,"*watch*") -> 14
A8: Postponed | B8: =COUNTIF(Calendar!$F$6:$F$52,"*Postponed*") -> 15
A9: Dates unconfirmed | B9: =COUNTIF(Calendar!$F$6:$F$52,"*unconfirmed*") -> 1
A10: KSA events | B10: =COUNTIF(Calendar!$G$6:$G$52,"KSA") -> 21
A11: GCC events | B11: =COUNTIF(Calendar!$G$6:$G$52,"GCC") -> 12
A12: MEA events | B12: =COUNTIF(Calendar!$G$6:$G$52,"MEA") -> 3
A13: Global events | B13: =COUNTIF(Calendar!$G$6:$G$52,"Global") -> 11
A15: Status colours
A16: Upcoming | C16: Confirmed on the official site or reputable press; no known risk
A17: At risk / watch | C17: Still scheduled, but security, venue or attendance risk; check daily
A18: Postponed | C18: Moved or cancelled; new dates shown where announced
A19: Dates unconfirmed | C19: No official confirmation yet; verify before planning
A20: Days to start, 0-7 | C20: Event starts within a week (countdown highlighted on the Calendar sheet)
A22: How this file is maintained
A23: Updated by the daily META Intel run (07:00 KSA) from the events and conferences agent (meta-events-intel).
A24: Source of truth: events_calendar.json in the same folder. This workbook is rebuilt from it by build-events-calendar.ps1, so edits made only in Excel are overwritten on the next run.
A25: Every date carries its source and the date it was verified. 'Days to start' recalculates from today's date each time the file is opened.
A26: Last updated: 2026-10-27.

Sheet Concluded
A1: Concluded events (last 60 days)
A3: Event | B3: Dates | C3: City / venue | D3: Outcome | E3: Source + verified on
A4: World Investment Forum 2026 (9th, UNCTAD) | B4: 25-27 Oct 2026 (live) | C4: Doha (venue not stated on UNCTAD page) | D4: UNCTAD reported new business projects declining despite rising FDI (27 Oct); Syria sought Qatari digital-infrastructure partners (secondary source). No GCC tech deals found. | E4: unctad.org WIF opening release, 25 Oct 2026 01:00 KSA
A5: Dubai AI Festival 2026 | B5: 26-27 Oct 2026 (live; earlier releases had said 7-8 Apr 2026) | C5: Dubai World Trade Centre | D5: Sheikh Hamdan set 2030 targets of 1,000+ AI firms and 5,000+ jobs; 500+ firms and Dh1bn+ reported achieved; new DIFC Zabeel District HQ reviewed. G42 CEO pitched the UAE as an exporter of intelligence. Scale AI UAE entity launched. HP the only PC OEM partner; no Lenovo presence; no hardware OEM deals. | E5: dubaiaifestival.com read 26 Oct 2026; The National 26 Oct 2026 18:37 KSA
A6: DCD>Connect MENA (+ DCD Investment Forum MENA 27 Oct) | B6: 26-27 Oct 2026 (live; Investment Forum 27 Oct) | C6: Dubai, Grand Hyatt | D6: Vendor releases only (Vertiv 360AI and SmartIT, Al Masaood Power). No Khazna, DataVolt, G42 or HUMAIN build announcements through 27 Oct 16:34 KSA. | E6: datacenterdynamics.com event page 24 Oct 2026; Zawya Vertiv release 26 Oct 09:30 KSA
A7: Milipol Qatar 2026 (16th) | B7: 20-22 Oct 2026 | C7: Doha, DECC | D7: 270+ exhibitors from 30+ countries; Qatar MOI-France 2027-30 action plan; Huawei showcase; Milipol Qatar 2028 announced; deal tally not published by 12:18 KSA 22 Oct; co-located Doha International Conference on AI & Security; Vodafone Qatar AI showcase; Huawei Gulf North AI-security pitch (Gulf Times 25 Oct) | E7: The Peninsula 22 Oct 12:09 KSA; Qatar Tribune 21 Oct; Xinhua 22 Oct
A8: WETEX 2026 + 12th World Green Economy Summit | B8: 20-22 Oct 2026 | C8: Dubai World Trade Centre | D8: DEWA/Moro Hub agreements with Huawei (ICT, servers, DC, cyber), Nozomi Networks and Syskey; DEWA International 4 MoUs (EDF, China Energy International, Capital Dynamics, TCS) | E8: WAM 21 Oct (c2us57j); WAM 20 Oct; Dubai Media Office 21 Oct
A9: NVIDIA GTC Berlin 2026 | B9: 46316 | C9: Berlin | D9: DSX POD launched (Lenovo a named partner); HUMAIN-DataVolt-Nebius 50 MW Oxagon framework signed on the sidelines; Aleria UAE GPU releases; Dell AI Factory line-up | E9: nvidianews.nvidia.com; NEOM newsroom; EIN Presswire; StorageReview, 21-22 Oct 2026
A10: Ai Everything Abu Dhabi | B10: 6-7 Oct 2026 | C10: Abu Dhabi, ADNEC Centre | D10: Dell-Tahaluf smart-city MoU signed there (OPP-079); Dell, HPE, Microsoft and G42 billed | E10: Gulf News, 24 Sep 2026; checked 18 Oct 2026
A11: World Petroleum Congress (Riyadh) | B11: 46306 | C11: Riyadh | D11: Went ahead; reportedly no executives from Shell, TotalEnergies, BP or ExxonMobil | E11: houseofsaud.com 18 Oct 2026 (uncited); Reuters via The Standard 14 Oct
A12: OCP Global Summit 2026 | B12: 12-15 Oct 2026 | C12: San Jose Convention Center | D12: Sold out; moves to Moscone, San Francisco from 2027; announcements not retrieved | E12: opencompute.org; checked 18 Oct 2026
A13: IMF/World Bank Annual Meetings 2026 | B13: Oct 2026 (exact dates not verified) | C13: Bangkok | D13: UAE signed to host the 2029 Annual Meetings in Abu Dhabi | E13: Zawya / Nation Thailand, 18 Oct 2026
A14: 30th GCC Ministerial Committee for Post and Telecommunications | B14: 46313 | C14: Bahrain | D14: MCIT's Alswaha offered sites and 14 GW of DC power to the GCC and proposed a GCC digital interconnection; bilaterals with Bahrain, Kuwait and Qatar | E14: SPA N2704500 and N2704449, 18 Oct 2026
A15: 6G MENA Summit (6G Summit in the AI Era) | B15: 19-20 Oct 2026 | C15: Abu Dhabi, Conrad Etihad Towers (per 6g-mena.com) | D15: TDRA (Dr Khalid Al Awadhi) set out the UAE 6G roadmap and standards role, expecting commercial 6G from 2030. No vendor deals reported from e&, du or Huawei. | E15: WAM 19 Oct 2026 18:47/18:52 KSA
A16: UAE-France Business Dialogue | B16: 46315 | C16: Abu Dhabi, Qasr Al Watan | D16: MBZUAI, G42 and Analog signed MoUs with AMI Labs; ADNOC Gas-Schneider Electric MoU; two ADNOC Refining-Technip Energies contracts. No values; hardware undisclosed. | E16: Abu Dhabi Media Office 20 Oct 2026 09:01 KSA
A17: Riyadh Season 2026 opening | B17: Opened 21 Oct 2026 | C17: Riyadh | D17: Opened 21 Oct; entertainment programme continues while business conferences in Riyadh are postponed. | E17: Asharq Al-Awsat 20 Oct 13:42 KSA; Al-Masry Al-Youm 20 Oct; SPA N2686677
A18: Saudi Maritime & Logistics Congress 2026 | B18: 21-22 Oct 2026 | C18: Jeddah Superdome | D18: Went ahead in Jeddah (Informa); deal tally not retrieved | E18: Seatrade Maritime Oct 2026
A19: ITCN Asia 2026 | B19: 22-24 Sep 2026 | C19: Karachi Expo Centre | D19: 800+ booths, SIFC collaboration; Cisco and Comtech Associates showcase | E19: Radio Pakistan 20 Sep 2026; Bloom Pakistan 24 Oct 2026

Sheet Change log
A1: Change log
A3: Date | B3: Change
A4: 46313 | B4: Calendar created from agent H's first sweep. FII10 and GITEX dates spot-checked on official sites. Recorded postponements: Saudi Build/Elenex (to Nov 2027), EU-GCC Summit (TBD), Six Kings Slam (to 27-30 Dec), ARTDOM Riyadh (to 2027).
A5: 46313 | B5: Moved to Excel: events_calendar.json is now the source of truth and META_Events_Calendar.xlsx is rebuilt from it by build-events-calendar.ps1.
A6: 46314 | B6: Global Health Exhibition moved 26-29 Oct 2026 to 25-28 Oct 2027 (globalhealthsaudi.com, notice undated). FII10 risk raised (WSJ 19 Oct; Etihad suspension to 24 Oct). Added Milipol Qatar, ADIPEC, Cairo ICT, Misk Global Forum (cancelled) and Riyadh Season opening (watch). Verified Expand North Star (8-10 Dec), ADFW (7-10 Dec) and Ignite (17-20 Nov). Replaced the DCD Connect Riyadh placeholder with DCD>Connect MENA (tentative). Moved Datacloud ME 2026 to concluded; logged the 18 Oct GCC telecom ministerial and the 11 Oct World Petroleum Congress as concluded.
A7: 46315 | B7: FII10 postponed to 2027 (dates TBA). Intersec Saudi Arabia (to Oct 2027) and Saudi Retail Forum (to Mar 2027) added as Postponed. Cairo ICT corrected to 7-10 Nov (official site). Riyadh Season opening 21 Oct confirmed. Cityscape, Black Hat MEA and ADIPEC re-verified on official sites. Added Apple Pro and tell (28 Oct), NVIDIA GTC DC (30 Nov-3 Dec) and ADSW 2027 (10-14 Jan). 6G MENA Summit and UAE-France Business Dialogue moved to concluded; Datacloud ME (Feb 2026) pruned.
A8: 46316 | B8: FII10 re-checked: still 2027, no dates. Added WETEX 2026 (20-22 Oct, live), Cityscape Qatar (27-29 Oct), Future Minerals Forum 2027 (12-14 Jan, KAICC), LEAP 2027 (dates unconfirmed) and Lenovo interim results (19 Nov, HKEX notice). Milipol Qatar updated (MOI-France 2027-30 action plan; Huawei showcase). Apple event city set to Los Angeles. GITEX re-verified (no Lenovo on sponsor page). Cityscape Global and Black Hat MEA set to at risk, watch (official sites 403; continuing strikes on Riyadh). DCD>Connect MENA still unconfirmed on the official site.
A9: 46317 | B9: DCD>Connect MENA confirmed 26-27 Oct, Grand Hyatt Dubai (official DCD page; Investment Forum 27 Oct). LEAP 2027 confirmed 12-15 Apr 2027 (onegiantleap.com). SC26 venue corrected to Chicago, McCormick Place. Cityscape Global and Black Hat MEA official sites live with no notice but kept at risk, watch (Skift corporate-travel freeze; US ordered departure of diplomats; Dammam airport strike). ADIPEC and ADFW re-confirmed (The National 22 Oct). Milipol Qatar, WETEX and GTC Berlin moved to concluded; Huawei-DEWA/Moro Hub ICT agreement logged. Biban still unconfirmed.
A10: 46319 | B10: Added MWC26 Doha (8-10 Nov), ITU PP-26 (9-27 Nov), World Police Summit (16-18 Nov), Data Center World ME (17-18 Nov), Touchdown ME (18-19 Nov); added UN World Data Forum + Saudi Statistics Forum (postponed to 2027) and IDEAS 2026 Karachi (cancelled, next 2028). Cairo ICT: Dell Title Sponsor, Huawei Technology Partner, no Lenovo. DCD>Connect MENA speakers updated (no server OEM). Cityscape Global speaker list updated; Cityscape and Black Hat MEA still at risk with no notice. Africa Tech Festival dates fixed to 17-19 Nov. Riyadh Season opening moved to concluded. Biban still unconfirmed.
A11: 46320 | B11: Added WIF 2026 Doha (live 25-27 Oct); GSTS Month (1-30 Nov), SAIF (24-26 Nov, moved from 19-21 Nov, RICEC) and GSTS Summit (18-20 Dec), all MOI/Tahaluf; SK hynix and Microsoft earnings (28 Oct); Samsung (29 Oct, unconfirmed); Security Middle East Conference postponed to 31 May 2027. Updated Cairo ICT sponsors (Fortinet; Cisco via CONNECT-PS), World Police Summit sponsors (Samsung headline, Presight), MWC26 Doha (co-located with ITU PP-26), GITEX bronze sponsors. Concluded: Saudi Maritime & Logistics Congress, ITCN Asia. Cityscape Global and Black Hat MEA sites 403, no notice found.
A12: 46321 | B12: Cityscape Global 2026 moved from 16-19 Nov 2026 to 1-4 Feb 2027 (Sabq 26 Oct 19:15 KSA; organiser notice undated); 2027 edition unchanged 15-18 Nov 2027. SAIF 24-26 Nov at RICEC confirmed, registration open (SPA N2710864). Black Hat MEA still 1-3 Dec with no notice, risk raised (same organiser and venue as Cityscape). Samsung Q3 call confirmed 29 Oct 10:00 KST. Added Dubai AI Festival (26-27 Oct, DWTC, live). MWC26 Doha sold out. DCD>Connect MENA and WIF live. ADIPEC and FII10 re-checked, no change; Biban still unconfirmed.
A13: 46322 | B13: Moved WIF, Dubai AI Festival and DCD>Connect MENA to concluded. GAIN Summit corrected: rescheduled to Sep 2027 (Arab News 1 Sep), concluded entry replaced with a Postponed row. Added Web Summit Lisbon (9-12 Nov), Asian Indoor & Martial Arts Games (Riyadh, to 28 Mar 2027) and FIA Extreme H Qiddiya (to 2027). GITEX sponsor list updated (Huawei Platinum, Supermicro/NVIDIA badge; no Lenovo, Dell, HP, HPE). Cityscape Qatar live. Biban 2026 still unconfirmed, likely stale listing. Samsung Q3 date conflict noted.
